README
setup.py
ezvirtualenv/__init__.py
ezvirtualenv.egg-info/PKG-INFO
ezvirtualenv.egg-info/SOURCES.txt
ezvirtualenv.egg-info/dependency_links.txt
ezvirtualenv.egg-info/requires.txt
ezvirtualenv.egg-info/top_level.txt