Metadata-Version: 1.1
Name: ezvirtualenv
Version: 0.1.3
Summary: Easy Virtual Environment
Home-page: https://github.com/matthiasmiller/ezvirtualenv
Author: Matthias Miller
Author-email: matthiasmiller@users.sf.net
License: UNKNOWN
Platform: UNKNOWN
Classifier: Development Status :: 3 - Alpha
Classifier: Intended Audience :: Developers
Classifier: License :: OSI Approved :: MIT License
Classifier: Programming Language :: Python :: 2.7
